sitreps_client/__init__.py
sitreps_client/cloc.py
sitreps_client/code_coverage.py
sitreps_client/exceptions.py
sitreps_client/issues.py
sitreps_client/project.py
sitreps_client/sonarqube.py
sitreps_client/unittests.py
sitreps_client/conf/config.py
sitreps_client/conf/default_settings.yaml
sitreps_client/utils/ci_downloader.py
sitreps_client/utils/helpers.py
sitreps_client/utils/path.py
sitreps_client/utils/repository.py
sitreps_client-3.1.0.dist-info/METADATA
sitreps_client-3.1.0.dist-info/WHEEL
sitreps_client-3.1.0.dist-info/licenses/LICENSE
sitreps_client-3.1.0.dist-info/RECORD
