Metadata-Version: 2.4
Name: sitreps-client
Version: 3.1.0
Summary: A client help to collect different metrics.
Project-URL: Source, https://github.com/digitronik/sitreps-client
Maintainer-email: Nikhil Dhandare <ndhandre@redhat.com>
License-Expression: MIT
License-File: LICENSE
Classifier: Development Status :: 4 - Beta
Classifier: Intended Audience :: Developers
Classifier: License :: OSI Approved :: MIT License
Classifier: Operating System :: OS Independent
Classifier: Programming Language :: Python
Classifier: Programming Language :: Python :: 3.8
Classifier: Programming Language :: Python :: 3.9
Classifier: Programming Language :: Python :: 3.10
Classifier: Programming Language :: Python :: Implementation :: CPython
Classifier: Programming Language :: Python :: Implementation :: PyPy
Classifier: Topic :: Software Development :: Testing
Requires-Dist: cached-property
Requires-Dist: jira
Requires-Dist: pygount
Requires-Dist: python-box
Requires-Dist: python-dotenv
Requires-Dist: python-sonarqube-api
Requires-Dist: pyyaml
Requires-Dist: requests
Provides-Extra: test
Requires-Dist: ipython; extra == 'test'
Requires-Dist: pre-commit; extra == 'test'
Requires-Dist: pytest; extra == 'test'
Requires-Dist: pytest-cov; extra == 'test'
Requires-Dist: pytest-xdist; extra == 'test'
